decafe_timer/__about__.py
decafe_timer/__init__.py
decafe_timer/cli.py
decafe_timer/duration.py
decafe_timer/main.py
decafe_timer-0.7.0.dist-info/METADATA
decafe_timer-0.7.0.dist-info/WHEEL
decafe_timer-0.7.0.dist-info/entry_points.txt
decafe_timer-0.7.0.dist-info/licenses/LICENSE.txt
decafe_timer-0.7.0.dist-info/RECORD
