Metadata-Version: 2.4
Name: decafe-timer
Version: 0.7.0
Summary: CLI coffee cooldown timer with a shrinking ASCII bar.
Project-URL: Issues, https://github.com/tos-kamiya/decafe-timer/issues
Project-URL: Source, https://github.com/tos-kamiya/decafe-timer
Author-email: Toshihiro Kamiya <kamiya@mbj.nifty.com>
License-Expression: MIT
License-File: LICENSE.txt
Keywords: cli,coffee,productivity,timer
Classifier: Development Status :: 4 - Beta
Classifier: Programming Language :: Python
Classifier: Programming Language :: Python :: 3.10
Classifier: Programming Language :: Python :: 3.11
Classifier: Programming Language :: Python :: 3.12
Classifier: Programming Language :: Python :: Implementation :: CPython
Requires-Python: >=3.10
Requires-Dist: appdirs
Provides-Extra: dev
Requires-Dist: pytest; extra == 'dev'
